Workbook

Sheet Raw Data
A1: Order ID | B1: Customer ID | C1: Customer Name | D1: Region | E1: City | F1: Category | G1: Product | H1: Quantity | I1: Unit Price | J1: Total Sales | K1: Profit | L1: Profit Margin % | M1: Month | N1: Quarter | O1: Payment Method
A2: 1001 | B2: 201 | C2: Rahul Sharma | D2: North | E2: Delhi | F2: Electronics | G2: Laptop | H2: 1 | I2: 45000 | J2: 45000 | K2: 9000 | L2: =K2/J2 -> 0.2 | M2: Jan | N2: Q1 | O2: Credit Card
A3: 1002 | B3: 202 | C3: Priya Singh | D3: West | E3: Mumbai | F3: Clothing | G3: Jacket | H3: 2 | I3: 1500 | J3: 3000 | K3: 450 | L3: =K3/J3 -> 0.15 | M3: Jan | N3: Q1 | O3: UPI
A4: 1003 | B4: 203 | C4: Amit Verma | D4: South | E4: Bangalore | F4: Electronics | G4: Phone | H4: 1 | I4: 20000 | J4: 20000 | K4: 3000 | L4: =K4/J4 -> 0.15 | M4: Jan | N4: Q1 | O4: Debit Card
A5: 1004 | B5: 201 | C5: Rahul Sharma | D5: North | E5: Delhi | F5: Books | G5: Data Science Book | H5: 3 | I5: 500 | J5: 1500 | K5: 300 | L5: =K5/J5 -> 0.2 | M5: Jan | N5: Q1 | O5: UPI
A6: 1005 | B6: 204 | C6: Sneha Patel | D6: West | E6: Ahmedabad | F6: Electronics | G6: Headphones | H6: 2 | I6: 2000 | J6: 4000 | K6: 800 | L6: =K6/J6 -> 0.2 | M6: Jan | N6: Q1 | O6: Credit Card
A7: 1006 | B7: 205 | C7: Vikram Nair | D7: South | E7: Chennai | F7: Clothing | G7: T-Shirt | H7: 5 | I7: 600 | J7: 3000 | K7: 600 | L7: =K7/J7 -> 0.2 | M7: Jan | N7: Q1 | O7: UPI
A8: 1007 | B8: 206 | C8: Anjali Mehta | D8: West | E8: Pune | F8: Home | G8: Table Lamp | H8: 1 | I8: 800 | J8: 800 | K8: 120 | L8: =K8/J8 -> 0.15 | M8: Jan | N8: Q1 | O8: Cash
A9: 1008 | B9: 202 | C9: Priya Singh | D9: West | E9: Mumbai | F9: Electronics | G9: Tablet | H9: 1 | I9: 15000 | J9: 15000 | K9: 2250 | L9: =K9/J9 -> 0.15 | M9: Feb | N9: Q1 | O9: Credit Card
A10: 1009 | B10: 207 | C10: Rohan Das | D10: East | E10: Kolkata | F10: Books | G10: Python Programming | H10: 2 | I10: 450 | J10: 900 | K10: 180 | L10: =K10/J10 -> 0.2 | M10: Feb | N10: Q1 | O10: UPI
A11: 1010 | B11: 208 | C11: Kavya Reddy | D11: South | E11: Hyderabad | F11: Home | G11: Curtains | H11: 3 | I11: 1200 | J11: 3600 | K11: 540 | L11: =K11/J11 -> 0.15 | M11: Feb | N11: Q1 | O11: Debit Card
A12: 1011 | B12: 203 | C12: Amit Verma | D12: South | E12: Bangalore | F12: Clothing | G12: Jeans | H12: 2 | I12: 1800 | J12: 3600 | K12: 720 | L12: =K12/J12 -> 0.2 | M12: Feb | N12: Q1 | O12: UPI
A13: 1012 | B13: 209 | C13: Neha Joshi | D13: North | E13: Delhi | F13: Electronics | G13: Smart Watch | H13: 1 | I13: 8000 | J13: 8000 | K13: 1600 | L13: =K13/J13 -> 0.2 | M13: Feb | N13: Q1 | O13: Credit Card
... A31: 1030 | B31: 212 | C31: Siddharth Roy | D31: East | E31: Kolkata | F31: Books | G31: Power BI Guide | H31: 2 | I31: 550 | J31: 1100 | K31: 220 | L31: =K31/J31 -> 0.2 | M31: Apr | N31: Q2 | O31: UPI

Sheet Summary Analysis
A1: SALES ANALYTICS — SUMMARY DASHBOARD
A3: KEY PERFORMANCE INDICATORS | E3: REVENUE BY CATEGORY
A4: Total Revenue | C4: =SUM('Raw Data'!J2:J31) -> 288750 | E4: Category | F4: Total Sales | G4: Total Profit | H4: % of Revenue
A5: Total Profit | C5: =SUM('Raw Data'!K2:K31) -> 53230 | E5: Electronics | F5: =SUMIF('Raw Data'!F:F,E5,'Raw Data'!J:J) -> 249000 | G5: =SUMIF('Raw Data'!F:F,E5,'Raw Data'!K:K) -> 46050 | H5: =F5/SUM(F5:F8) -> 0.86233766
A6: Avg Order Value | C6: =AVERAGE('Raw Data'!J2:J31) -> 9625 | E6: Clothing | F6: =SUMIF('Raw Data'!F:F,E6,'Raw Data'!J:J) -> 21400 | G6: =SUMIF('Raw Data'!F:F,E6,'Raw Data'!K:K) -> 4130 | H6: =F6/SUM(F5:F8) -> 0.074112554
A7: Total Orders | C7: =COUNTA('Raw Data'!A2:A31) -> 30 | E7: Home | F7: =SUMIF('Raw Data'!F:F,E7,'Raw Data'!J:J) -> 12400 | G7: =SUMIF('Raw Data'!F:F,E7,'Raw Data'!K:K) -> 1860 | H7: =F7/SUM(F5:F8) -> 0.042943723
A8: Avg Profit Margin | C8: =AVERAGE('Raw Data'!L2:L31) -> 0.18 | E8: Books | F8: =SUMIF('Raw Data'!F:F,E8,'Raw Data'!J:J) -> 5950 | G8: =SUMIF('Raw Data'!F:F,E8,'Raw Data'!K:K) -> 1190 | H8: =F8/SUM(F5:F8) -> 0.020606061
A9: Top Category | C9: =INDEX('Raw Data'!F2:F31,MATCH(MAX(SUMIF('Raw Data'!F2:F31,'Raw Data'!F2:F31,'Raw Data'!J2:J31)),SUMIF('Raw Data'!F2:F31,'Raw Data'!F2:F31,'Raw Data'!J2:J31),0)) -> Electronics | E9: TOTAL | F9: =SUM(F5:F8) -> 288750 | G9: =SUM(G5:G8) -> 53230 | H9: =SUM(H5:H8) -> 1
A11: REVENUE BY REGION | E11: MONTHLY REVENUE TREND
A12: Region | B12: Revenue | C12: Orders | E12: Month | F12: Orders | G12: Revenue | H12: Profit
A13: North | B13: =SUMIF('Raw Data'!D:D,A13,'Raw Data'!J:J) -> 133500 | C13: =COUNTIF('Raw Data'!D:D,A13) -> 9 | E13: Jan | F13: =COUNTIF('Raw Data'!M:M,E13) -> 7 | G13: =SUMIF('Raw Data'!M:M,E13,'Raw Data'!J:J) -> 77300 | H13: =SUMIF('Raw Data'!M:M,E13,'Raw Data'!K:K) -> 14270
A14: South | B14: =SUMIF('Raw Data'!D:D,A14,'Raw Data'!J:J) -> 99900 | C14: =COUNTIF('Raw Data'!D:D,A14) -> 9 | E14: Feb | F14: =COUNTIF('Raw Data'!M:M,E14) -> 7 | G14: =SUMIF('Raw Data'!M:M,E14,'Raw Data'!J:J) -> 33500 | H14: =SUMIF('Raw Data'!M:M,E14,'Raw Data'!K:K) -> 5680
A15: West | B15: =SUMIF('Raw Data'!D:D,A15,'Raw Data'!J:J) -> 47250 | C15: =COUNTIF('Raw Data'!D:D,A15) -> 8 | E15: Mar | F15: =COUNTIF('Raw Data'!M:M,E15) -> 8 | G15: =SUMIF('Raw Data'!M:M,E15,'Raw Data'!J:J) -> 95400 | H15: =SUMIF('Raw Data'!M:M,E15,'Raw Data'!K:K) -> 17805
A16: East | B16: =SUMIF('Raw Data'!D:D,A16,'Raw Data'!J:J) -> 8100 | C16: =COUNTIF('Raw Data'!D:D,A16) -> 4 | E16: Apr | F16: =COUNTIF('Raw Data'!M:M,E16) -> 8 | G16: =SUMIF('Raw Data'!M:M,E16,'Raw Data'!J:J) -> 82550 | H16: =SUMIF('Raw Data'!M:M,E16,'Raw Data'!K:K) -> 15475

Sheet Top Customers
A1: TOP CUSTOMER ANALYSIS
A2: Rank | B2: Customer Name | C2: City | D2: Total Orders | E2: Total Spent
A3: 1 | B3: Meera Iyer | C3: Chennai | D3: 2 | E3: 53200
A4: 2 | B4: Aditya Singh | C4: Delhi | D4: 1 | E4: 48000
A5: 3 | B5: Rahul Sharma | C5: Delhi | D5: 2 | E5: 46500
A6: 4 | B6: Anjali Mehta | C6: Pune | D6: 2 | E6: 22800
A7: 5 | B7: Arjun Kapoor | C7: Jaipur | D7: 2 | E7: 19800
A8: 6 | B8: Divya Nair | C8: Bangalore | D8: 1 | E8: 9500
A9: 7 | B9: Neha Joshi | C9: Delhi | D9: 2 | E9: 9500
A10: 8 | B10: Karan Malhotra | C10: Delhi | D10: 1 | E10: 7500
A11: 9 | B11: Kavya Reddy | C11: Hyderabad | D11: 2 | E11: 9600
A12: 10 | B12: Priya Singh | C12: Mumbai | D12: 2 | E12: 18000

Sheet Power BI Steps
A1: POWER BI DASHBOARD — STEP BY STEP GUIDE
A2: Step | B2: Action
A3: STEP 1 | B3: Open Power BI Desktop → Get Data → Excel → Select this file → Load 'Raw Data' sheet
A4: STEP 2 | B4: Go to Transform Data (Power Query) → Check column types → Close & Apply
A5: STEP 3 | B5: Create Measure: Total Revenue = SUM('Raw Data'[Total Sales])
A6: STEP 4 | B6: Create Measure: Total Profit = SUM('Raw Data'[Profit])
A7: STEP 5 | B7: Create Measure: Avg Order Value = AVERAGE('Raw Data'[Total Sales])
A8: STEP 6 | B8: Create Measure: Profit Margin % = DIVIDE([Total Profit],[Total Revenue])
A9: STEP 7 | B9: Add 4 KPI Cards → Total Revenue, Total Profit, Avg Order Value, Total Orders
A10: STEP 8 | B10: Add Clustered Bar Chart → Axis: Category → Values: Total Revenue
A11: STEP 9 | B11: Add Line Chart → Axis: Month → Values: Total Revenue
A12: STEP 10 | B12: Add Donut Chart → Legend: Region → Values: Total Revenue
A13: STEP 11 | B13: Add Stacked Bar → Axis: City → Values: Total Sales
... A17: STEP 15 | B17: Save as .pbix → Take screenshot → Upload to GitHub
